data/ipm_regions_simple.geojson
data/additional_technologies/AZ_additional_tech.csv
data/additional_technologies/AZ_additional_tech_2030.csv
data/additional_technologies/AZ_additional_tech_2045.csv
data/additional_technologies/additional tech documentation.md
data/additional_technologies/sample_additional_tech.csv
data/coal_fgd/fgd_output.csv
data/cost_multipliers/AEO_2020_regional_cost_corrections.csv
data/cost_multipliers/EIA regional cost multipliers.csv
data/cpi_data/cpi_data.csv
powergenome/.coveragerc
powergenome/GenX.py
powergenome/__init__.py
powergenome/cluster_method.py
powergenome/co2_pipeline_cost.py
powergenome/debug.py
powergenome/distributed_gen.py
powergenome/eia_opendata.py
powergenome/external_data.py
powergenome/extract_pudl_data.py
powergenome/financials.py
powergenome/fuels.py
powergenome/generators.py
powergenome/load_construction.py
powergenome/load_profiles.py
powergenome/nrelatb.py
powergenome/params.py
powergenome/price_adjustment.py
powergenome/resource_clusters.py
powergenome/run_powergenome_multiple_outputs_cli.py
powergenome/time_reduction.py
powergenome/transmission.py
powergenome/util.py
powergenome/version.py
powergenome/cluster/renewables.py
powergenome-0.7.0.dist-info/METADATA
powergenome-0.7.0.dist-info/WHEEL
powergenome-0.7.0.dist-info/entry_points.txt
powergenome-0.7.0.dist-info/licenses/LICENSE.md
powergenome-0.7.0.dist-info/RECORD
