Metadata-Version: 2.4
Name: PowerGenome
Version: 0.7.0
Summary: Create power system inputs for capacity expansion models
Project-URL: Source, https://github.com/PowerGenome/PowerGenome
Author-email: Greg Schivley <greg.schivley@princeton.edu>
Maintainer-email: Greg Schivley <greg.schivley@princeton.edu>
License: MIT
License-File: LICENSE.md
Keywords: capacity expansion,power system data,two
Classifier: Development Status :: 4 - Beta
Classifier: Environment :: Console
Classifier: Intended Audience :: Science/Research
Classifier: License :: OSI Approved :: MIT License
Classifier: Natural Language :: English
Classifier: Operating System :: OS Independent
Classifier: Programming Language :: Python
Classifier: Programming Language :: Python :: 3
Classifier: Topic :: Scientific/Engineering
Requires-Python: >=3.8
Requires-Dist: beautifulsoup4>=4.8.13
Requires-Dist: catalystcoop-pudl<=2022.11.30,>=0.6.0
Requires-Dist: duckdb
Requires-Dist: flatten-dict
Requires-Dist: frozendict
Requires-Dist: geopandas>=0.12
Requires-Dist: openpyxl>=3.0
Requires-Dist: pyarrow
Requires-Dist: pyogrio
Requires-Dist: python-dotenv
Requires-Dist: pyyaml
Requires-Dist: ruamel-yaml
Requires-Dist: statsmodels>=0.12.2
Requires-Dist: xlrd
Provides-Extra: dev
Requires-Dist: black[jupyter]==24.3.0; extra == 'dev'
Requires-Dist: build; extra == 'dev'
Requires-Dist: isort; extra == 'dev'
Requires-Dist: pre-commit; extra == 'dev'
Requires-Dist: pytest; extra == 'dev'
Requires-Dist: twine; extra == 'dev'
